yscoverage/__init__.py
yscoverage/_version.py
yscoverage/analytics.py
yscoverage/apps.py
yscoverage/coverage.py
yscoverage/dataset.py
yscoverage/get2edit.py
yscoverage/mappings.py
yscoverage/mibyang.py
yscoverage/paw_wrapper.py
yscoverage/precommit.py
yscoverage/urls.py
yscoverage/views.py
yscoverage/xpathdata.py
yscoverage/yangdiff.py
yscoverage/mibs/ACCOUNTING-CONTROL-MIB.my
yscoverage/mibs/ACTONA-ACTASTOR-MIB.my
yscoverage/mibs/ADMIN-AUTH-STATS-MIB.my
yscoverage/mibs/ADSL-DMT-LINE-MIB.my
yscoverage/mibs/ADSL-LINE-MIB.my
yscoverage/mibs/ADSL-TC-MIB.my
yscoverage/mibs/ADSL2-LINE-MIB.my
yscoverage/mibs/ADSL2-LINE-TC-MIB.my
yscoverage/mibs/AGENTX-MIB.txt
yscoverage/mibs/AIRESPACE-REF-MIB.my
yscoverage/mibs/AIRESPACE-SWITCHING-MIB.my
yscoverage/mibs/AIRESPACE-WIRELESS-MIB.my
yscoverage/mibs/AIRPORT-BASESTATION-3-MIB.txt
yscoverage/mibs/ALTIGA-ADDRESS-STATS-MIB.my
yscoverage/mibs/ALTIGA-BMGT-STATS-MIB.my
yscoverage/mibs/ALTIGA-CAP.my
yscoverage/mibs/ALTIGA-CERT-STATS-MIB.my
yscoverage/mibs/ALTIGA-DHCP-SERVER-STATS-MIB.my
yscoverage/mibs/ALTIGA-DHCP-STATS-MIB.my
yscoverage/mibs/ALTIGA-DNS-STATS-MIB.my
yscoverage/mibs/ALTIGA-EVENT-STATS-MIB.my
yscoverage/mibs/ALTIGA-FILTER-STATS-MIB.my
yscoverage/mibs/ALTIGA-FTP-STATS-MIB.my
yscoverage/mibs/ALTIGA-GENERAL-STATS-MIB.my
yscoverage/mibs/ALTIGA-GLOBAL-REG.my
yscoverage/mibs/ALTIGA-HARDWARE-STATS-MIB.my
yscoverage/mibs/ALTIGA-HTTP-STATS-MIB.my
yscoverage/mibs/ALTIGA-IP-STATS-MIB.my
yscoverage/mibs/ALTIGA-L2TP-STATS-MIB.my
yscoverage/mibs/ALTIGA-LBSSF-STATS-MIB.my
yscoverage/mibs/ALTIGA-MIB.my
yscoverage/mibs/ALTIGA-MULTILINK-STATS-MIB.my
yscoverage/mibs/ALTIGA-NAT-STATS-MIB.my
yscoverage/mibs/ALTIGA-PPP-STATS-MIB.my
yscoverage/mibs/ALTIGA-PPPOE-STATS-MIB.my
yscoverage/mibs/ALTIGA-PPTP-STATS-MIB.my
yscoverage/mibs/ALTIGA-SDI-ACE-STATS-MIB.my
yscoverage/mibs/ALTIGA-SEP-STATS-MIB.my
yscoverage/mibs/ALTIGA-SESSION-STATS-MIB.my
yscoverage/mibs/ALTIGA-SSH-STATS-MIB.my
yscoverage/mibs/ALTIGA-SSL-STATS-MIB.my
yangsuite_coverage-3.0.11.dist-info/LICENSE.txt
yangsuite_coverage-3.0.11.dist-info/METADATA
yangsuite_coverage-3.0.11.dist-info/WHEEL
yangsuite_coverage-3.0.11.dist-info/entry_points.txt
yangsuite_coverage-3.0.11.dist-info/top_level.txt
yangsuite_coverage-3.0.11.dist-info/RECORD
