Metadata-Version: 2.1
Name: yangsuite-coverage
Version: 3.0.11
Summary: Check Cisco CLI config for YANG coverage in an IOS release.
Home-page: https://developer.cisco.com/yangsuite
Author: Michael Ott
Author-email: yang-suite-dev@cisco.com
License: Cisco End User License Agreement
License-File: LICENSE.txt
Requires-Dist: yangsuite (>=2.0.0)
Requires-Dist: yangsuite-yangtree (>=2.0.0)
Requires-Dist: yangsuite-filemanager (<2.0.0,>=1.5.0)
Requires-Dist: yangsuite-devices (<3.0.0,>=2.0.0)
Requires-Dist: yangsuite-netconf (<2.0.0,>=1.0.0)
Requires-Dist: requests (<3.0)
Requires-Dist: docker (<5.0.0)
Requires-Dist: pandas (<2.0.0)
Requires-Dist: elasticsearch (<8.0.0)
Requires-Dist: markupsafe (<2.1.0)
Requires-Dist: openpyxl
Requires-Dist: xlsxwriter
